verify_crypto_signature/__init__.py
verify_crypto_signature/evm.py
verify_crypto_signature/py.typed
verify_crypto_signature/sol.py
verify_crypto_signature-0.0.1.dist-info/licenses/LICENSE
verify_crypto_signature-0.0.1.dist-info/METADATA
verify_crypto_signature-0.0.1.dist-info/WHEEL
verify_crypto_signature-0.0.1.dist-info/top_level.txt
verify_crypto_signature-0.0.1.dist-info/RECORD
