Metadata-Version: 2.4
Name: verify-crypto-signature
Version: 0.0.1
Summary: A comprehensive Python library to verify crypto wallet signatures
Home-page: https://github.com/walver-io/verify-crypto-signature
Author: BonifacioCalindoro
Author-email: admin@walver.io
Keywords: verify,crypto,signature,wallet,blockchain,solana,ethereum,cryptography
Classifier: Development Status :: 3 - Alpha
Classifier: Intended Audience :: Developers
Classifier: License :: OSI Approved :: MIT License
Classifier: Programming Language :: Python :: 3
Classifier: Programming Language :: Python :: 3.7
Classifier: Programming Language :: Python :: 3.8
Classifier: Programming Language :: Python :: 3.9
Classifier: Programming Language :: Python :: 3.10
Classifier: Programming Language :: Python :: 3.11
Classifier: Programming Language :: Python :: 3.12
Classifier: Programming Language :: Python :: 3.13
Classifier: Operating System :: OS Independent
Classifier: Topic :: Software Development :: Libraries :: Python Modules
Classifier: Typing :: Typed
Requires-Python: >=3.7
License-File: LICENSE
Requires-Dist: annotated-types==0.7.0
Requires-Dist: bitarray==3.4.0
Requires-Dist: ckzg==2.1.1
Requires-Dist: cytoolz==1.0.1
Requires-Dist: eth-account==0.13.7
Requires-Dist: eth-hash==0.7.1
Requires-Dist: eth-keyfile==0.8.1
Requires-Dist: eth-keys==0.7.0
Requires-Dist: eth-rlp==2.2.0
Requires-Dist: eth-typing==5.2.1
Requires-Dist: eth-utils==5.3.0
Requires-Dist: eth_abi==5.2.0
Requires-Dist: hexbytes==1.3.0
Requires-Dist: jsonalias==0.1.1
Requires-Dist: parsimonious==0.10.0
Requires-Dist: pycryptodome==3.22.0
Requires-Dist: pydantic==2.11.4
Requires-Dist: pydantic_core==2.33.2
Requires-Dist: regex==2024.11.6
Requires-Dist: rlp==4.1.0
Requires-Dist: solders==0.26.0
Requires-Dist: toolz==1.0.0
Requires-Dist: typing-inspection==0.4.0
Requires-Dist: typing_extensions==4.13.2
Dynamic: author
Dynamic: author-email
Dynamic: classifier
Dynamic: description
Dynamic: description-content-type
Dynamic: home-page
Dynamic: keywords
Dynamic: license-file
Dynamic: requires-dist
Dynamic: requires-python
Dynamic: summary
